setup.py
sentryflo/__init__.py
sentryflo.egg-info/PKG-INFO
sentryflo.egg-info/SOURCES.txt
sentryflo.egg-info/dependency_links.txt
sentryflo.egg-info/entry_points.txt
sentryflo.egg-info/not-zip-safe
sentryflo.egg-info/requires.txt
sentryflo.egg-info/top_level.txt
sentryflo/amazon_sns/__init__.py
sentryflo/amazon_sns/plugin.py