Metadata-Version: 1.0
Name: sentryflo
Version: 0.1.dev0
Summary: Sentry plugin to forward events via SNS
Home-page: https://github.com/CharlieR-o-o-t/test-task
Author: Siarhei Rasiukevich
Author-email: me.sudo.su@gmail.com
License: Apache
Platform: UNKNOWN
